{\n  "project": "MASIA - Caso Salto",\n  "description": "Esquema de datos para el análisis del conflicto Intendencia de Salto vs. ADEOMS (292 cesados)",\n  "author": "José H. González",\n  "date_created": "2025-08-25",\n  "data_layers": [\n    {\n      "layer_name": "medios_digitales",\n      "description": "Artículos de diarios y portales digitales",\n      "source": ["El Pueblo Digital", "Cambio Digital", "Tiempo de Noticias", "Cero Estrés"],\n      "fields": [\n        {"name": "id", "type": "string", "description": "Identificador único del artículo"},\n        {"name": "url", "type": "string", "description": "URL del artículo"},\n        {"name": "fecha_publicacion", "type": "date", "description": "Fecha de publicación"},\n        {"name": "titulo", "type": "string", "description": "Título del artículo"},\n        {"name": "autor", "type": "string", "description": "Autor del artículo"},\n        {"name": "contenido", "type": "text", "description": "Texto completo del artículo"},\n        {"name": "frame_dominante", "type": "string", "description": "Frame principal identificado"},\n        {"name": "tema_principal", "type": "string", "description": "Tema central del artículo"}\n      ]\n    },\n    {\n      "layer_name": "redes_sociales",\n      "description": "Posts y comentarios públicos de Facebook relacionados con el conflicto",\n      "source": ["Facebook"],\n      "fields": [\n        {"name": "id", "type": "string", "description": "Identificador único del post o comentario"},\n        {"name": "usuario_anon", "type": "string", "description": "Usuario anonimizdo"},\n        {"name": "fecha_post", "type": "date", "description": "Fecha del post/comentario"},\n        {"name": "contenido", "type": "text", "description": "Texto del post/comentario"},\n        {"name": "sentimiento", "type": "string", "description": "Clasificación de sentimiento (positivo, negativo, neutral)"},\n        {"name": "frame_detectado", "type": "string", "description": "Frame narrativo detectado en el texto"}\n      ]\n    },\n    {\n      "layer_name": "actores_institucionales",\n      "description": "Declaraciones oficiales de la Intendencia y ADEOMS",\n      "source": ["Comunicados oficiales", "Prensa institucional"],\n      "fields": [\n        {"name": "id", "type": "string", "description": "Identificador único del comunicado"},\n        {"name": "emisor", "type": "string", "description": "Entidad que emite el comunicado"},\n        {"name": "fecha", "type": "date", "description": "Fecha de emisión"},\n        {"name": "contenido", "type": "text", "description": "Texto del comunicado"},\n        {"name": "frame_dominante", "type": "string", "description": "Frame dominante en la comunicación"},\n        {"name": "tema", "type": "string", "description": "Tema central del comunicado"}\n      ]\n    }\n  ],\n  "notes": "Todos los datos que contengan información personal serán anonimizados. El esquema puede ampliarse según nuevas capas de información o fuentes."\n}